haros/__init__.py
haros/__main__.py
haros/analysis_manager.py
haros/cmake_parser.py
haros/config_builder.py
haros/data.py
haros/definitions.yaml
haros/export_manager.py
haros/extractor.py
haros/haros.py
haros/hpl_parser.py
haros/launch_parser.py
haros/metamodel.py
haros/plugin_manager.py
haros/pyflwor_monkey_patch.py
haros/util.py
haros/visualiser.py
haros/models/controller_manager.yaml
haros/models/diagnostic_aggregator.yaml
haros/models/hector_mapping.yaml
haros/models/husky_base.yaml
haros/models/interactive_marker_twist_server.yaml
haros/models/joy.yaml
haros/models/lms1xx.yaml
haros/models/map_server.yaml
haros/models/move_base.yaml
haros/models/nodelet.yaml
haros/models/prosilica_camera.yaml
haros/models/robot_localization.yaml
haros/models/robot_state_publisher.yaml
haros/models/teleop_twist_joy.yaml
haros/models/template.yaml
haros/models/tf.yaml
harosviz/index.html
harosviz/css/color.css
harosviz/css/style.css
harosviz/css/type.css
harosviz/js/app.js
harosviz/js/models.js
harosviz/js/routes.js
harosviz/js/views/dashboard.js
harosviz/js/views/general.js
harosviz/js/views/help.js
harosviz/js/views/issues.js
harosviz/js/views/packages.js
harosviz/js/views/ros.js
harosviz/lib/css/font-awesome.min.css
harosviz/lib/css/grids-responsive-min.css
harosviz/lib/css/pure-min.css
harosviz/lib/fonts/fontawesome-webfont.eot
harosviz/lib/fonts/fontawesome-webfont.svg
harosviz/lib/fonts/fontawesome-webfont.ttf
harosviz/lib/fonts/fontawesome-webfont.woff
harosviz/lib/fonts/fontawesome-webfont.woff2
harosviz/lib/js/backbone.min.js
harosviz/lib/js/d3.min.js
harosviz/lib/js/dagre.min.js
harosviz/lib/js/jquery-2.2.1.min.js
harosviz/lib/js/underscore.min.js
haros-3.10.20.dist-info/LICENSE
haros-3.10.20.dist-info/METADATA
haros-3.10.20.dist-info/WHEEL
haros-3.10.20.dist-info/entry_points.txt
haros-3.10.20.dist-info/top_level.txt
haros-3.10.20.dist-info/zip-safe
haros-3.10.20.dist-info/RECORD
