Metadata-Version: 2.1
Name: haros
Version: 3.10.20
Summary: Static analysis framework for ROS
Home-page: https://github.com/git-afsantos/haros
Author: André Santos
Author-email: haros.framework@gmail.com
License: MIT
Keywords: static-analysis ros
Platform: UNKNOWN
Requires-Dist: pyyaml
Requires-Dist: rospkg
Requires-Dist: python-magic
Requires-Dist: bonsai-code (<1.0.0,>=0.6.7)
Requires-Dist: haros-plugins (<2.0.0,>=1.0.3)
Requires-Dist: hpl-specs
Requires-Dist: ros-type-tokens
